rtspscanner.py
rtspscanner-0.1.5.dist-info/LICENSE
rtspscanner-0.1.5.dist-info/METADATA
rtspscanner-0.1.5.dist-info/WHEEL
rtspscanner-0.1.5.dist-info/entry_points.txt
rtspscanner-0.1.5.dist-info/top_level.txt
rtspscanner-0.1.5.dist-info/RECORD
