Metadata-Version: 2.1
Name: rtspscanner
Version: 0.1.5
Summary: RTSP Camera Scanner
Home-page: https://github.com/beardedtek-com/RTSPScanner
Author: The Bearded Tek
Author-email: kenny@beardedtek.com
License: AGPLv3
Project-URL: Bug Tracker, https://github.com/beardedtek-com/RTSPScanner/issues
Keywords: port,scanner,multithreading,queue,terminal,utility,rtsp,camera,frigate,fevr,beardedtek,python3,cctv,security
Classifier: Environment :: Console
Classifier: License :: OSI Approved :: GNU Affero General Public License v3 or later (AGPLv3+)
Classifier: Natural Language :: English
Classifier: Operating System :: MacOS :: MacOS X
Classifier: Operating System :: POSIX
Classifier: Operating System :: POSIX :: Linux
Classifier: Programming Language :: Python :: 3
Classifier: Topic :: Utilities
Classifier: Topic :: Home Automation
Classifier: Topic :: Software Development :: Libraries :: Python Modules
Classifier: Topic :: System :: Networking
Classifier: Topic :: Multimedia :: Video
Classifier: Topic :: Multimedia :: Video :: Capture
License-File: LICENSE
Requires-Dist: beard-portscan
Requires-Dist: Pillow
